bex/__init__.py
bex/benchmark.py
bex/datasets.py
bex/explainers/__init__.py
bex/explainers/base.py
bex/explainers/dice.py
bex/explainers/dive.py
bex/explainers/gs.py
bex/explainers/informed.py
bex/explainers/latent_cf.py
bex/explainers/stylex.py
bex/explainers/xgem.py
bex/loggers/__init__.py
bex/loggers/loggers.py
bex/models/__init__.py
bex/models/backbones.py
bex/models/classifier.py
bex/models/configs.py
bex/models/encoder.py
bex/models/generator.py
bex-0.14.dist-info/LICENSE
bex-0.14.dist-info/METADATA
bex-0.14.dist-info/WHEEL
bex-0.14.dist-info/top_level.txt
bex-0.14.dist-info/RECORD
