Metadata-Version: 2.1
Name: bex
Version: 0.14
Summary: Benchmark for explainability methods in computer vision
Home-page: https://anonymous.4open.science/r/Bex-15A3/
Author: Anonymous
Author-email: 
Classifier: Programming Language :: Python :: 3
Classifier: License :: OSI Approved :: Apache Software License
Classifier: Operating System :: Unix
Requires-Python: >=3.6
License-File: LICENSE
Requires-Dist: torch
Requires-Dist: h5py
Requires-Dist: pandas
Requires-Dist: scipy
Requires-Dist: torchvision
Requires-Dist: haven-ai
Requires-Dist: requests
